HyperSloth/__init__.py
HyperSloth/_debug_dataloader.py
HyperSloth/_patch_log.py
HyperSloth/dataset_utils.py
HyperSloth/example_training_config.py
HyperSloth/hp_trainer_setup.py
HyperSloth/hypersloth_config.py
HyperSloth/init_modules.py
HyperSloth/logging_config.py
HyperSloth/mmap_gradient_sync.py
HyperSloth/nccl_grad_sync.py
HyperSloth/patching/__init__.py
HyperSloth/patching/inner_training_loop.py
HyperSloth/patching/patch_sampler.py
HyperSloth/scripts/build_dataset_hf.py
HyperSloth/scripts/build_dataset_sharegpt.py
HyperSloth/scripts/export.py
HyperSloth/scripts/get_example_config.py
HyperSloth/scripts/hp_trainer.py
HyperSloth/scripts/packing.py
hypersloth-0.1.1.dist-info/LICENSE
hypersloth-0.1.1.dist-info/METADATA
hypersloth-0.1.1.dist-info/WHEEL
hypersloth-0.1.1.dist-info/entry_points.txt
hypersloth-0.1.1.dist-info/RECORD
