Metadata-Version: 2.3
Name: hypersloth
Version: 0.1.1
Summary: A high-performance framework for fine-tuning large language models with multi-GPU support
License: MIT
Keywords: machine learning,deep learning,transformers,fine-tuning,multi-gpu,llm
Author: anhvth
Author-email: anhvth.226@gmail.com
Requires-Python: >=3.9
Classifier: Development Status :: 4 - Beta
Classifier: Intended Audience :: Developers
Classifier: Intended Audience :: Science/Research
Classifier: License :: OSI Approved :: MIT License
Classifier: Operating System :: OS Independent
Classifier: Programming Language :: Python :: 3
Classifier: Programming Language :: Python :: 3.9
Classifier: Programming Language :: Python :: 3.10
Classifier: Programming Language :: Python :: 3.11
Classifier: Programming Language :: Python :: 3.12
Classifier: Topic :: Scientific/Engineering :: Artificial Intelligence
Classifier: Topic :: Software Development :: Libraries :: Python Modules
Requires-Dist: fastcore (>=1.7.29,<2.0.0)
Requires-Dist: fire (>=0.7.0,<0.8.0)
Requires-Dist: jupyterlab (>=4.3.5,<5.0.0)
Requires-Dist: pyyaml (>=6.0.2,<7.0.0)
Requires-Dist: speedy-utils (>=0.1.20,<0.2.0)
Requires-Dist: tensorboard (>=2.19.0,<3.0.0)
Requires-Dist: tensorboardx (>=2.6.2.2,<3.0.0.0)
Project-URL: Bug Tracker, https://github.com/anhvth/hypersloth/issues
Project-URL: Documentation, https://github.com/anhvth/hypersloth
Project-URL: Homepage, https://github.com/anhvth/hypersloth
Project-URL: Repository, https://github.com/anhvth/hypersloth
